{
  "city": {
    "money": 10764,
    "happiness": 0.48000000000000026,
    "population": 35,
    "house_count": 0,
    "store_count": 0,
    "factory_count": 0,
    "city_jobs": 39
  },
  "demand": {
    "residential": 4.022,
    "commercial": 17.5,
    "industrial": 5.25
  },
  "grid": [
    [
      null,
      null,
      null,
      null,
      {
        "type": "VerticalRoad",
        "name": "Vertical Road"
      },
      {
        "type": "VerticalRoad",
        "name": "Vertical Road"
      },
      null,
      null,
      null,
      null
    ],
    [
      {
        "type": "Tree",
        "name": "Tree"
      },
      null,
      null,
      null,
      {
        "type": "VerticalRoad",
        "name": "Vertical Road"
      },
      {
        "type": "VerticalRoad",
        "name": "Vertical Road"
      },
      null,
      null,
      {
        "type": "Tree",
        "name": "Tree"
      },
      null
    ],
    [
      null,
      {
        "type": "Tree",
        "name": "Tree"
      },
      null,
      null,
      {
        "type": "VerticalRoad",
        "name": "Vertical Road"
      },
      {
        "type": "VerticalRoad",
        "name": "Vertical Road"
      },
      null,
      null,
      null,
      null
    ],
    [
      null,
      null,
      null,
      null,
      {
        "type": "VerticalRoad",
        "name": "Vertical Road"
      },
      {
        "type": "VerticalRoad",
        "name": "Vertical Road"
      },
      null,
      null,
      null,
      null
    ],
    [
      null,
      null,
      null,
      {
        "type": "House",
        "name": "House",
        "income": 0,
        "happiness": 0.01,
        "population": 7,
        "open_positions": 0,
        "build_time": 1,
        "remaining_time": -0.0021000000051571988,
        "built": true
      },
      {
        "type": "VerticalRoad",
        "name": "Vertical Road"
      },
      {
        "type": "VerticalRoad",
        "name": "Vertical Road"
      },
      {
        "type": "Factory",
        "name": "Factory",
        "income": 28,
        "happiness": 0.0,
        "population": 0,
        "open_positions": 11,
        "build_time": 5,
        "remaining_time": -0.010000916001445148,
        "built": true
      },
      null,
      null,
      null
    ],
    [
      null,
      null,
      {
        "type": "House",
        "name": "House",
        "income": 0,
        "happiness": 0.01,
        "population": 9,
        "open_positions": 0,
        "build_time": 1,
        "remaining_time": -0.0020984999937354587,
        "built": true
      },
      {
        "type": "House",
        "name": "House",
        "income": 0,
        "happiness": 0.01,
        "population": 10,
        "open_positions": 0,
        "build_time": 1,
        "remaining_time": -0.0021000000051571988,
        "built": true
      },
      {
        "type": "VerticalRoad",
        "name": "Vertical Road"
      },
      {
        "type": "VerticalRoad",
        "name": "Vertical Road"
      },
      {
        "type": "Factory",
        "name": "Factory",
        "income": 26,
        "happiness": 0.0,
        "population": 0,
        "open_positions": 19,
        "build_time": 5,
        "remaining_time": -0.009999707996030338,
        "built": true
      },
      {
        "type": "Water",
        "name": "Water"
      },
      {
        "type": "Water",
        "name": "Water"
      },
      {
        "type": "Water",
        "name": "Water"
      }
    ],
    [
      null,
      null,
      null,
      {
        "type": "House",
        "name": "House",
        "income": 0,
        "happiness": 0.01,
        "population": 9,
        "open_positions": 0,
        "build_time": 1,
        "remaining_time": -0.0020008749997941777,
        "built": true
      },
      {
        "type": "VerticalRoad",
        "name": "Vertical Road"
      },
      {
        "type": "VerticalRoad",
        "name": "Vertical Road"
      },
      {
        "type": "Factory",
        "name": "Factory",
        "income": 34,
        "happiness": 0.0,
        "population": 0,
        "open_positions": 9,
        "build_time": 5,
        "remaining_time": -0.009999707996030338,
        "built": true
      },
      {
        "type": "Water",
        "name": "Water"
      },
      {
        "type": "Water",
        "name": "Water"
      },
      {
        "type": "Water",
        "name": "Water"
      }
    ],
    [
      null,
      null,
      {
        "type": "Tree",
        "name": "Tree"
      },
      null,
      {
        "type": "VerticalRoad",
        "name": "Vertical Road"
      },
      {
        "type": "VerticalRoad",
        "name": "Vertical Road"
      },
      null,
      {
        "type": "Water",
        "name": "Water"
      },
      {
        "type": "Water",
        "name": "Water"
      },
      {
        "type": "Water",
        "name": "Water"
      }
    ],
    [
      null,
      null,
      null,
      null,
      {
        "type": "VerticalRoad",
        "name": "Vertical Road"
      },
      {
        "type": "VerticalRoad",
        "name": "Vertical Road"
      },
      null,
      null,
      {
        "type": "Tree",
        "name": "Tree"
      },
      {
        "type": "Tree",
        "name": "Tree"
      }
    ],
    [
      null,
      null,
      null,
      null,
      {
        "type": "VerticalRoad",
        "name": "Vertical Road"
      },
      {
        "type": "VerticalRoad",
        "name": "Vertical Road"
      },
      null,
      null,
      null,
      null
    ]
  ],
  "buildings": [
    {
      "building": {
        "type": "House",
        "name": "House",
        "income": 0,
        "happiness": 0.01,
        "population": 9,
        "open_positions": 0,
        "build_time": 1,
        "remaining_time": -0.0020984999937354587,
        "built": true
      },
      "x": 2,
      "y": 5
    },
    {
      "building": {
        "type": "House",
        "name": "House",
        "income": 0,
        "happiness": 0.01,
        "population": 7,
        "open_positions": 0,
        "build_time": 1,
        "remaining_time": -0.0021000000051571988,
        "built": true
      },
      "x": 3,
      "y": 4
    },
    {
      "building": {
        "type": "House",
        "name": "House",
        "income": 0,
        "happiness": 0.01,
        "population": 10,
        "open_positions": 0,
        "build_time": 1,
        "remaining_time": -0.0021000000051571988,
        "built": true
      },
      "x": 3,
      "y": 5
    },
    {
      "building": {
        "type": "House",
        "name": "House",
        "income": 0,
        "happiness": 0.01,
        "population": 9,
        "open_positions": 0,
        "build_time": 1,
        "remaining_time": -0.0020008749997941777,
        "built": true
      },
      "x": 3,
      "y": 6
    },
    {
      "building": {
        "type": "Factory",
        "name": "Factory",
        "income": 26,
        "happiness": 0.0,
        "population": 0,
        "open_positions": 19,
        "build_time": 5,
        "remaining_time": -0.009999707996030338,
        "built": true
      },
      "x": 6,
      "y": 5
    },
    {
      "building": {
        "type": "Factory",
        "name": "Factory",
        "income": 34,
        "happiness": 0.0,
        "population": 0,
        "open_positions": 9,
        "build_time": 5,
        "remaining_time": -0.009999707996030338,
        "built": true
      },
      "x": 6,
      "y": 6
    },
    {
      "building": {
        "type": "Factory",
        "name": "Factory",
        "income": 28,
        "happiness": 0.0,
        "population": 0,
        "open_positions": 11,
        "build_time": 5,
        "remaining_time": -0.010000916001445148,
        "built": true
      },
      "x": 6,
      "y": 4
    }
  ],
  "timestamp": 1765575944.74145
}